psycodanticpg/__init__.py
psycodanticpg/__main__.py
psycodanticpg/objects/__init__.py
psycodanticpg/objects/database.py
psycodanticpg/objects/database_schema.py
psycodanticpg/objects/database_schema_column.py
psycodanticpg/objects/database_schema_source.py
psycodanticpg/objects/database_schema_table.py
psycodanticpg/objects/database_schemas.py
psycodanticpg/objects/database_url.py
psycodanticpg/objects/schema_connection.py
psycodanticpg/objects/schema_cursor.py
psycodanticpg/objects/schema_sql.py
psycodanticpg/objects/schema_sql_fieldtype.py
psycodanticpg/objects/some_schema.py
psycodanticpg/objects/sql.py
psycodanticpg/objects/sql_queries.py
psycodanticpg/objects/sql_tablename.py
psycodanticpg/objects/t.py
psycodanticpg/scripts/__init__.py
psycodanticpg/scripts/generate_schemas.py
psycodanticpg/scripts/util/__init__.py
psycodanticpg/scripts/util/args.py
psycodanticpg/sql/database_schemas.sql
psycodanticpg/sql/drop_tables.sql
psycodanticpg/sql/select_public_table_names.sql
psycodanticpg/sql/select_version.sql
psycodanticpg-0.0.8.dist-info/METADATA
psycodanticpg-0.0.8.dist-info/WHEEL
psycodanticpg-0.0.8.dist-info/RECORD
