Metadata-Version: 2.1
Name: psycodanticpg
Version: 0.0.8
Summary: psycopg2 database utilizing pydantic models
License: MIT
Author: wayfaring-stranger
Author-email: zw6p226m@duck.com
Requires-Python: >=3.9,<4.0
Classifier: License :: OSI Approved :: MIT License
Classifier: Programming Language :: Python :: 3
Classifier: Programming Language :: Python :: 3.9
Classifier: Programming Language :: Python :: 3.10
Classifier: Programming Language :: Python :: 3.11
Requires-Dist: psycopg2-binary (>=2.9.5,<3.0.0)
Requires-Dist: pydantic (>=1.10.2,<2.0.0)
Requires-Dist: python-dotenv (==1.0.0)
